odoo/addons/mgmtsystem_nonconformity_hr/README.rst
odoo/addons/mgmtsystem_nonconformity_hr/__init__.py
odoo/addons/mgmtsystem_nonconformity_hr/__manifest__.py
odoo/addons/mgmtsystem_nonconformity_hr/i18n/es.po
odoo/addons/mgmtsystem_nonconformity_hr/i18n/it.po
odoo/addons/mgmtsystem_nonconformity_hr/i18n/mgmtsystem_extended_hr.pot
odoo/addons/mgmtsystem_nonconformity_hr/i18n/mgmtsystem_nonconformity_hr.pot
odoo/addons/mgmtsystem_nonconformity_hr/i18n/pt.po
odoo/addons/mgmtsystem_nonconformity_hr/models/__init__.py
odoo/addons/mgmtsystem_nonconformity_hr/models/mgmtsystem_nonconformity_hr.py
odoo/addons/mgmtsystem_nonconformity_hr/readme/CONTRIBUTORS.rst
odoo/addons/mgmtsystem_nonconformity_hr/readme/DESCRIPTION.rst
odoo/addons/mgmtsystem_nonconformity_hr/readme/HISTORY.rst
odoo/addons/mgmtsystem_nonconformity_hr/readme/USAGE.rst
odoo/addons/mgmtsystem_nonconformity_hr/static/description/icon.png
odoo/addons/mgmtsystem_nonconformity_hr/static/description/index.html
odoo/addons/mgmtsystem_nonconformity_hr/views/mgmtsystem_nonconformity_views.xml
odoo14_addon_mgmtsystem_nonconformity_hr-14.0.1.0.1.dev9.dist-info/METADATA
odoo14_addon_mgmtsystem_nonconformity_hr-14.0.1.0.1.dev9.dist-info/WHEEL
odoo14_addon_mgmtsystem_nonconformity_hr-14.0.1.0.1.dev9.dist-info/top_level.txt
odoo14_addon_mgmtsystem_nonconformity_hr-14.0.1.0.1.dev9.dist-info/RECORD
